datametria_common/__init__.py
datametria_common/backend/api_framework/__init__.py
datametria_common/backend/api_framework/app.py
datametria_common/backend/api_framework/decorators.py
datametria_common/backend/api_framework/dependencies.py
datametria_common/backend/api_framework/exceptions.py
datametria_common/backend/api_framework/middleware.py
datametria_common/backend/api_framework/models.py
datametria_common/backend/api_framework/responses.py
datametria_common/backend/authentication/__init__.py
datametria_common/backend/authentication/auth_manager.py
datametria_common/backend/authentication/decorators.py
datametria_common/backend/authentication/dependencies.py
datametria_common/backend/authentication/jwt_manager.py
datametria_common/backend/authentication/models.py
datametria_common/backend/rate_limiting/__init__.py
datametria_common/backend/rate_limiting/decorators.py
datametria_common/backend/rate_limiting/middleware.py
datametria_common/backend/rate_limiting/models.py
datametria_common/backend/rate_limiting/rate_limiter.py
datametria_common/backend/rate_limiting/strategies.py
datametria_common/caching/cache_mixins.py
datametria_common/caching/unified_cache.py
datametria_common/cloud/aws/__init__.py
datametria_common/cloud/aws/cloudwatch.py
datametria_common/cloud/aws/config.py
datametria_common/cloud/aws/eventbridge.py
datametria_common/cloud/aws/lambda_manager.py
datametria_common/cloud/aws/manager.py
datametria_common/cloud/aws/models.py
datametria_common/cloud/aws/rds.py
datametria_common/cloud/aws/s3.py
datametria_common/cloud/aws/scheduler.py
datametria_common/cloud/aws/secrets.py
datametria_common/cloud/aws/stepfunctions.py
datametria_common/cloud/gcp/__init__.py
datametria_common/cloud/gcp/bigquery.py
datametria_common/cloud/gcp/config.py
datametria_common/cloud/gcp/firebase_auth.py
datametria_common/cloud/gcp/firestore.py
datametria_common/cloud/gcp/functions.py
datametria_common/cloud/gcp/manager.py
datametria_common/cloud/gcp/monitoring.py
datametria_common_libraries-1.1.1.dist-info/entry_points.txt
datametria_common_libraries-1.1.1.dist-info/licenses/LICENSE
datametria_common_libraries-1.1.1.dist-info/METADATA
datametria_common_libraries-1.1.1.dist-info/WHEEL
datametria_common_libraries-1.1.1.dist-info/RECORD
