Metadata-Version: 2.4
Name: datametria-common-libraries
Version: 1.1.1
Summary: Stack Multi-Tecnologia Enterprise-Ready - Conjunto abrangente de módulos, classes, ferramentas e bibliotecas reutilizáveis para desenvolvimento enterprise
License-Expression: MIT
License-File: LICENSE
Keywords: datametria,enterprise,oracle,database,security,lgpd,gdpr,compliance,cloud,aws,gcp,azure
Author: Vander Loto
Author-email: vander.loto@datametria.io
Maintainer: DATAMETRIA Enterprise Team
Maintainer-email: suporte@datametria.io
Requires-Python: >=3.11
Classifier: Development Status :: 5 - Production/Stable
Classifier: Intended Audience :: Developers
Classifier: Operating System :: OS Independent
Classifier: Programming Language :: Python :: 3
Classifier: Programming Language :: Python :: 3.11
Classifier: Programming Language :: Python :: 3.12
Classifier: Topic :: Database
Classifier: Topic :: Security
Classifier: Topic :: Software Development :: Libraries :: Python Modules
Classifier: Topic :: System :: Systems Administration
Provides-Extra: all
Provides-Extra: all-cloud
Provides-Extra: all-databases
Provides-Extra: api
Provides-Extra: aws
Provides-Extra: azure
Provides-Extra: cache
Provides-Extra: data
Provides-Extra: gcp
Provides-Extra: monitoring
Provides-Extra: oracle
Provides-Extra: postgresql
Provides-Extra: sqlserver
Provides-Extra: vault
Provides-Extra: workspace
Requires-Dist: alembic (>=1.14.0,<2.0.0)
Requires-Dist: asyncpg ; extra == "all"
Requires-Dist: asyncpg ; extra == "all-databases"
Requires-Dist: asyncpg ; extra == "postgresql"
Requires-Dist: azure-identity ; extra == "all"
Requires-Dist: azure-identity ; extra == "all-cloud"
Requires-Dist: azure-identity ; extra == "azure"
Requires-Dist: azure-storage-blob ; extra == "all"
Requires-Dist: azure-storage-blob ; extra == "all-cloud"
Requires-Dist: azure-storage-blob ; extra == "azure"
Requires-Dist: bcrypt (>=5.0.0,<6.0.0)
Requires-Dist: boto3 ; extra == "all"
Requires-Dist: boto3 ; extra == "all-cloud"
Requires-Dist: boto3 ; extra == "aws"
Requires-Dist: botocore ; extra == "all"
Requires-Dist: botocore ; extra == "all-cloud"
Requires-Dist: botocore ; extra == "aws"
Requires-Dist: cryptography (>=46.0.0,<47.0.0)
Requires-Dist: cx-oracle ; extra == "all"
Requires-Dist: cx-oracle ; extra == "all-databases"
Requires-Dist: cx-oracle ; extra == "oracle"
Requires-Dist: fastapi ; extra == "all"
Requires-Dist: fastapi ; extra == "api"
Requires-Dist: firebase-admin ; extra == "all"
Requires-Dist: firebase-admin ; extra == "all-cloud"
Requires-Dist: firebase-admin ; extra == "gcp"
Requires-Dist: google-api-python-client ; extra == "all"
Requires-Dist: google-api-python-client ; extra == "all-cloud"
Requires-Dist: google-api-python-client ; extra == "workspace"
Requires-Dist: google-auth ; extra == "all"
Requires-Dist: google-auth ; extra == "all-cloud"
Requires-Dist: google-auth ; extra == "workspace"
Requires-Dist: google-auth-httplib2 ; extra == "all"
Requires-Dist: google-auth-httplib2 ; extra == "all-cloud"
Requires-Dist: google-auth-httplib2 ; extra == "workspace"
Requires-Dist: google-auth-oauthlib ; extra == "all"
Requires-Dist: google-auth-oauthlib ; extra == "all-cloud"
Requires-Dist: google-auth-oauthlib ; extra == "workspace"
Requires-Dist: google-cloud-bigquery ; extra == "all"
Requires-Dist: google-cloud-bigquery ; extra == "all-cloud"
Requires-Dist: google-cloud-bigquery ; extra == "gcp"
Requires-Dist: google-cloud-firestore ; extra == "all"
Requires-Dist: google-cloud-firestore ; extra == "all-cloud"
Requires-Dist: google-cloud-firestore ; extra == "gcp"
Requires-Dist: google-cloud-functions ; extra == "all"
Requires-Dist: google-cloud-functions ; extra == "all-cloud"
Requires-Dist: google-cloud-functions ; extra == "gcp"
Requires-Dist: google-cloud-storage ; extra == "all"
Requires-Dist: google-cloud-storage ; extra == "all-cloud"
Requires-Dist: google-cloud-storage ; extra == "gcp"
Requires-Dist: hiredis ; extra == "all"
Requires-Dist: hiredis ; extra == "cache"
Requires-Dist: httpx (>=0.28.0,<0.29.0)
Requires-Dist: hvac ; extra == "all"
Requires-Dist: hvac ; extra == "vault"
Requires-Dist: numpy ; extra == "all"
Requires-Dist: numpy ; extra == "data"
Requires-Dist: oracledb ; extra == "all"
Requires-Dist: oracledb ; extra == "all-databases"
Requires-Dist: oracledb ; extra == "oracle"
Requires-Dist: pandas ; extra == "all"
Requires-Dist: pandas ; extra == "data"
Requires-Dist: passlib[bcrypt] (>=1.7.4,<2.0.0)
Requires-Dist: prometheus-client ; extra == "all"
Requires-Dist: prometheus-client ; extra == "monitoring"
Requires-Dist: psycopg2-binary ; extra == "all"
Requires-Dist: psycopg2-binary ; extra == "all-databases"
Requires-Dist: psycopg2-binary ; extra == "postgresql"
Requires-Dist: pydantic (>=2.10.0,<3.0.0)
Requires-Dist: pyjwt[crypto] (>=2.10.0,<3.0.0)
Requires-Dist: pyodbc ; extra == "all"
Requires-Dist: pyodbc ; extra == "all-databases"
Requires-Dist: pyodbc ; extra == "sqlserver"
Requires-Dist: python-dotenv (>=1.0.0,<2.0.0)
Requires-Dist: pytz (>=2025.2,<2026.0)
Requires-Dist: redis ; extra == "all"
Requires-Dist: redis ; extra == "cache"
Requires-Dist: requests (>=2.32.0,<3.0.0)
Requires-Dist: sentry-sdk ; extra == "all"
Requires-Dist: sentry-sdk ; extra == "monitoring"
Requires-Dist: sqlalchemy (>=2.0.0,<3.0.0)
Requires-Dist: starlette ; extra == "all"
Requires-Dist: starlette ; extra == "api"
Requires-Dist: structlog (>=25.4.0,<26.0.0)
Requires-Dist: uvicorn ; extra == "all"
Requires-Dist: uvicorn ; extra == "api"
Project-URL: Bug Tracker, https://github.com/datametria/DATAMETRIA-common-libraries/issues
Project-URL: Changelog, https://github.com/datametria/DATAMETRIA-common-libraries/blob/main/CHANGELOG.md
Project-URL: Documentation, https://datametria.github.io/DATAMETRIA-common-libraries
Project-URL: Funding, https://github.com/sponsors/datametria
Project-URL: Homepage, https://github.com/datametria/DATAMETRIA-common-libraries
Project-URL: Repository, https://github.com/datametria/DATAMETRIA-common-libraries
Project-URL: Source, https://github.com/datametria/DATAMETRIA-common-libraries
